saa/__init__.py
saa/checks.py
saa/cli.py
saa/config.py
saa/crawler.py
saa/llm.py
saa/models.py
saa/plan.py
saa/report.py
saa/data/__init__.py
saa/data/default-audit-plan.md
site_audit_agent-0.5.1.dist-info/METADATA
site_audit_agent-0.5.1.dist-info/WHEEL
site_audit_agent-0.5.1.dist-info/entry_points.txt
site_audit_agent-0.5.1.dist-info/licenses/LICENSE
site_audit_agent-0.5.1.dist-info/RECORD
