Metadata-Version: 2.4
Name: site-audit-agent
Version: 0.5.1
Summary: Site Audit Agent - CLI tool for automated website audits
License-Expression: GPL-3.0-or-later
License-File: LICENSE
Requires-Python: >=3.10
Requires-Dist: beautifulsoup4>=4.12.0
Requires-Dist: click>=8.1.0
Requires-Dist: lxml>=5.0.0
Requires-Dist: playwright-stealth>=1.0.0
Requires-Dist: playwright>=1.40.0
Requires-Dist: pydantic>=2.5.0
Requires-Dist: python-dotenv>=1.0.0
Requires-Dist: pyyaml>=6.0.0
Requires-Dist: requests>=2.31.0
Provides-Extra: dev
Requires-Dist: pytest-asyncio>=0.23.0; extra == 'dev'
Requires-Dist: pytest>=7.0.0; extra == 'dev'
